episim37/__init__.py
episim37/alias_table.py
episim37/ast.py
episim37/check_ast.py
episim37/cli.py
episim37/click_helpers.py
episim37/codegen_openmp.py
episim37/input_helpers.py
episim37/language_server.py
episim37/misc.py
episim37/output_helpers.py
episim37/parse_tree.py
episim37/tree_sitter_bindings.py
episim37/utils.py
episim37/static/simulation_common_openmp.h
episim37/templates/apply_statement_defn_openmp.jinja2
episim37/templates/apply_statement_launch_openmp.jinja2
episim37/templates/call_statement.jinja2
episim37/templates/cmakelists_txt_openmp.jinja2
episim37/templates/contagion_methods.jinja2
episim37/templates/discrete_dist_defn.jinja2
episim37/templates/edge_table_defn.jinja2
episim37/templates/enum_defn.jinja2
episim37/templates/function_decl.jinja2
episim37/templates/function_defn.jinja2
episim37/templates/global_defn.jinja2
episim37/templates/if_statement.jinja2
episim37/templates/node_table_defn.jinja2
episim37/templates/normal_dist_defn.jinja2
episim37/templates/pass_statement.jinja2
episim37/templates/print_statement.jinja2
episim37/templates/reduce_statement_defn_openmp.jinja2
episim37/templates/reduce_statement_launch_openmp.jinja2
episim37/templates/return_statement.jinja2
episim37/templates/sample_statement_launch_openmp.jinja2
episim37/templates/select_statement_defn_openmp.jinja2
episim37/templates/select_statement_launch_openmp.jinja2
episim37/templates/simulator_openmp.jinja2
episim37/templates/switch_statement.jinja2
episim37/templates/uniform_dist_defn.jinja2
episim37/templates/update_statement.jinja2
episim37/templates/variable.jinja2
episim37/templates/while_loop.jinja2
episim37/tree-sitter-esl37/src/grammar.json
episim37/tree-sitter-esl37/src/node-types.json
episim37/tree-sitter-esl37/src/parser.c
episim37/tree-sitter-esl37/src/tree_sitter/parser.h
episim37-0.1.2.dist-info/LICENSE
episim37-0.1.2.dist-info/METADATA
episim37-0.1.2.dist-info/WHEEL
episim37-0.1.2.dist-info/entry_points.txt
episim37-0.1.2.dist-info/top_level.txt
episim37-0.1.2.dist-info/RECORD
